[ {
  "x" : 0,
  "y" : 0,
  "color" : "#FF0000",
  "username" : "blindpirate"
}, {
  "x" : 0,
  "y" : 1,
  "color" : "#FF0000",
  "username" : "wangjie-fourth"
}, {
  "x" : 0,
  "y" : 2,
  "color" : "#b36d61",
  "username" : "OpaqueWhite"
}, {
  "x" : 0,
  "y" : 3,
  "color" : "#b36d61",
  "username" : "shanghaox"
}, {
  "x" : 0,
  "y" : 4,
  "color" : "#FFFFFF",
  "username" : "wangwang123gg"
}, {
  "x" : 0,
  "y" : 5,
  "color" : "#ADD8E6",
  "username" : "StargazerSylpha"
}, {
  "x" : 0,
  "y" : 6,
  "color" : "#FF0000",
  "username" : "EastZhang"
}, {
  "x" : 0,
  "y" : 7,
  "color" : "#111111",
  "username" : "Ascaris-Equi"
}, {
  "x" : 0,
  "y" : 8,
  "color" : "#FFFFFF",
  "username" : "qishiazusa"
}, {
  "x" : 0,
  "y" : 9,
  "color" : "#ff8c11",
  "username" : "ggymm"
}, {
  "x" : 0,
  "y" : 10,
  "color" : "#FFFFFF",
  "username" : "viperasi"
}, {
  "x" : 0,
  "y" : 12,
  "color" : "#3489fd",
  "username" : "Tsanfer"
}, {
  "x" : 0,
  "y" : 13,
  "color" : "#00CCFF",
  "username" : "Queel123"
}, {
  "x" : 0,
  "y" : 14,
  "color" : "#F5F5F5",
  "username" : "freefrank"
}, {
  "x" : 0,
  "y" : 16,
  "color" : "#000011",
  "username" : "kerwin-cn"
}, {
  "x" : 0,
  "y" : 18,
  "color" : "#FF9900",
  "username" : "Alibion"
}, {
  "x" : 0,
  "y" : 19,
  "color" : "#66CCFF",
  "username" : "wanghewen"
}, {
  "x" : 1,
  "y" : 0,
  "color" : "#228B22",
  "username" : "jaryarbn"
}, {
  "x" : 1,
  "y" : 1,
  "color" : "#FFFFFF",
  "username" : "shiliyu"
}, {
  "x" : 1,
  "y" : 2,
  "color" : "#FAFAFA",
  "username" : "qazwhy123"
}, {
  "x" : 1,
  "y" : 3,
  "color" : "#b36d61",
  "username" : "ayi1001"
}, {
  "x" : 1,
  "y" : 4,
  "color" : "#FF00F0",
  "username" : "o0hana"
}, {
  "x" : 1,
  "y" : 6,
  "color" : "#F5F5F5",
  "username" : "geekqiao"
}, {
  "x" : 1,
  "y" : 8,
  "color" : "#FFDA53",
  "username" : "anyueye"
}, {
  "x" : 1,
  "y" : 12,
  "color" : "#000000",
  "username" : "HermanVong"
}, {
  "x" : 1,
  "y" : 13,
  "color" : "#8EE4FA",
  "username" : "Gakiii"
}, {
  "x" : 1,
  "y" : 15,
  "color" : "#00FFFF",
  "username" : "lineazy"
}, {
  "x" : 1,
  "y" : 17,
  "color" : "#000000",
  "username" : "Galaxy-ghost"
}, {
  "x" : 1,
  "y" : 18,
  "color" : "#111111",
  "username" : "miueon"
}, {
  "x" : 1,
  "y" : 19,
  "color" : "#02a2ff",
  "username" : "2333hbg"
}, {
  "x" : 2,
  "y" : 0,
  "color" : "#ffffff",
  "username" : "feng-siwei"
}, {
  "x" : 2,
  "y" : 1,
  "color" : "#F4F5F6",
  "username" : "DC1024"
}, {
  "x" : 2,
  "y" : 2,
  "color" : "#FF9900",
  "username" : "kalac2232"
}, {
  "x" : 2,
  "y" : 5,
  "color" : "#FFFFFF",
  "username" : "SaionChi"
}, {
  "x" : 2,
  "y" : 10,
  "color" : "#00CCFF",
  "username" : "keroro2021"
}, {
  "x" : 2,
  "y" : 16,
  "color" : "#00CCFF",
  "username" : "xenphane"
}, {
  "x" : 3,
  "y" : 0,
  "color" : "#666666",
  "username" : "gtn1024"
}, {
  "x" : 3,
  "y" : 1,
  "color" : "#666666",
  "username" : "greek-zzf"
}, {
  "x" : 3,
  "y" : 2,
  "color" : "#000000",
  "username" : "dfgedc"
}, {
  "x" : 3,
  "y" : 3,
  "color" : "#666666",
  "username" : "Zengtianshunyi"
}, {
  "x" : 3,
  "y" : 4,
  "color" : "#F0F0F0",
  "username" : "yiqilaiYishi"
}, {
  "x" : 3,
  "y" : 5,
  "color" : "#EEEEE0",
  "username" : "OKLetsPEE"
}, {
  "x" : 3,
  "y" : 6,
  "color" : "#FFB6C1",
  "username" : "CoolLoong"
}, {
  "x" : 3,
  "y" : 7,
  "color" : "#FFFFFF",
  "username" : "gylt37"
}, {
  "x" : 3,
  "y" : 8,
  "color" : "#000000",
  "username" : "achenjs"
}, {
  "x" : 3,
  "y" : 10,
  "color" : "#87CEFA",
  "username" : "LAW-NBJ"
}, {
  "x" : 3,
  "y" : 12,
  "color" : "#000000",
  "username" : "zjpazyh"
}, {
  "x" : 3,
  "y" : 13,
  "color" : "#009688",
  "username" : "ddlmq"
}, {
  "x" : 3,
  "y" : 15,
  "color" : "#FFE2FE",
  "username" : "jilucky"
}, {
  "x" : 3,
  "y" : 16,
  "color" : "#FFFFFF",
  "username" : "skywhat"
}, {
  "x" : 3,
  "y" : 19,
  "color" : "#CFE2F3",
  "username" : "FormatToday"
}, {
  "x" : 4,
  "y" : 0,
  "color" : "#0000FF",
  "username" : "sweetln"
}, {
  "x" : 4,
  "y" : 1,
  "color" : "#000000",
  "username" : "shikaiguo"
}, {
  "x" : 4,
  "y" : 2,
  "color" : "#1C3E49",
  "username" : "xwj001"
}, {
  "x" : 4,
  "y" : 4,
  "color" : "#FF9800",
  "username" : "JB962"
}, {
  "x" : 4,
  "y" : 6,
  "color" : "#FFB6C1",
  "username" : "Kiriyor"
}, {
  "x" : 4,
  "y" : 8,
  "color" : "#0000FF",
  "username" : "AranaQAQ"
}, {
  "x" : 4,
  "y" : 14,
  "color" : "#FFFFFF",
  "username" : "Break00"
}, {
  "x" : 5,
  "y" : 0,
  "color" : "#0000FF",
  "username" : "Howard-Zhou-77"
}, {
  "x" : 5,
  "y" : 1,
  "color" : "#39c5bb",
  "username" : "ginwAa"
}, {
  "x" : 5,
  "y" : 2,
  "color" : "#FFFFFF",
  "username" : "ubc2"
}, {
  "x" : 5,
  "y" : 3,
  "color" : "#FF0000",
  "username" : "dzzhyk"
}, {
  "x" : 5,
  "y" : 4,
  "color" : "#87CEFA",
  "username" : "breakToT"
}, {
  "x" : 5,
  "y" : 5,
  "color" : "#000000",
  "username" : "oooooutsider"
}, {
  "x" : 5,
  "y" : 10,
  "color" : "#87CEFA",
  "username" : "kain-hao"
}, {
  "x" : 5,
  "y" : 12,
  "color" : "#F00000",
  "username" : "salaku001"
}, {
  "x" : 5,
  "y" : 15,
  "color" : "#101010",
  "username" : "xiangming1975"
}, {
  "x" : 6,
  "y" : 0,
  "color" : "#66ffcc",
  "username" : "RC-Kanashii"
}, {
  "x" : 6,
  "y" : 1,
  "color" : "#000000",
  "username" : "xjiazhi"
}, {
  "x" : 6,
  "y" : 2,
  "color" : "#87CEFA",
  "username" : "tianyu-monica"
}, {
  "x" : 6,
  "y" : 3,
  "color" : "#39C5BB",
  "username" : "ParasolGao"
}, {
  "x" : 6,
  "y" : 5,
  "color" : "#FFE2FE",
  "username" : "tracywong117"
}, {
  "x" : 6,
  "y" : 6,
  "color" : "#666666",
  "username" : "hah1346798520"
}, {
  "x" : 6,
  "y" : 7,
  "color" : "#FF00F0",
  "username" : "hbc13579"
}, {
  "x" : 6,
  "y" : 8,
  "color" : "#FFC0CB",
  "username" : "xuyupeng1995"
}, {
  "x" : 6,
  "y" : 9,
  "color" : "#C3EDC7",
  "username" : "beidongjiedeguang"
}, {
  "x" : 6,
  "y" : 10,
  "color" : "#87CEFA",
  "username" : "CatMoe"
}, {
  "x" : 6,
  "y" : 11,
  "color" : "#FE7FF0",
  "username" : "LCymd"
}, {
  "x" : 6,
  "y" : 14,
  "color" : "#1A2B3C",
  "username" : "Moooooontreal"
}, {
  "x" : 6,
  "y" : 16,
  "color" : "#1F1E33",
  "username" : "Ruri1101"
}, {
  "x" : 6,
  "y" : 18,
  "color" : "#FF0000",
  "username" : "XiakaiPan"
}, {
  "x" : 6,
  "y" : 19,
  "color" : "#000001",
  "username" : "xu-fan"
}, {
  "x" : 7,
  "y" : 0,
  "color" : "#000000",
  "username" : "z77881200"
}, {
  "x" : 7,
  "y" : 1,
  "color" : "#ACACAC",
  "username" : "2337533962"
}, {
  "x" : 7,
  "y" : 4,
  "color" : "#39C5BB",
  "username" : "huhuhu8"
}, {
  "x" : 7,
  "y" : 6,
  "color" : "#00CCFF",
  "username" : "Carven-Huang"
}, {
  "x" : 7,
  "y" : 7,
  "color" : "#ffffcc",
  "username" : "wjl-lab"
}, {
  "x" : 7,
  "y" : 8,
  "color" : "#ff0000",
  "username" : "hausir"
}, {
  "x" : 7,
  "y" : 9,
  "color" : "#FFC0CB",
  "username" : "Vanlle"
}, {
  "x" : 7,
  "y" : 10,
  "color" : "#FF0000",
  "username" : "orange2002"
}, {
  "x" : 7,
  "y" : 11,
  "color" : "#000000",
  "username" : "Keswill"
}, {
  "x" : 7,
  "y" : 12,
  "color" : "#FF0000",
  "username" : "watermelonyyy"
}, {
  "x" : 7,
  "y" : 19,
  "color" : "#93DB70",
  "username" : "Long6688k"
}, {
  "x" : 8,
  "y" : 0,
  "color" : "#000FFF",
  "username" : "Oppus"
}, {
  "x" : 8,
  "y" : 1,
  "color" : "#114514",
  "username" : "lbr77"
}, {
  "x" : 8,
  "y" : 2,
  "color" : "#63CCFF",
  "username" : "vadedeloewen"
}, {
  "x" : 8,
  "y" : 3,
  "color" : "#000000",
  "username" : "daoBrother"
}, {
  "x" : 8,
  "y" : 5,
  "color" : "#F5F5F5",
  "username" : "wuxujiaren"
}, {
  "x" : 8,
  "y" : 6,
  "color" : "#F5F5F5",
  "username" : "Jackson0913"
}, {
  "x" : 8,
  "y" : 7,
  "color" : "#FFC0CB",
  "username" : "sybarite1"
}, {
  "x" : 8,
  "y" : 8,
  "color" : "#000000",
  "username" : "kisslonglin"
}, {
  "x" : 8,
  "y" : 9,
  "color" : "#66CCFF",
  "username" : "zhy910827"
}, {
  "x" : 8,
  "y" : 10,
  "color" : "#FFFFFF",
  "username" : "jonsnowljs"
}, {
  "x" : 8,
  "y" : 11,
  "color" : "#00000F",
  "username" : "yangzhoucyl"
}, {
  "x" : 8,
  "y" : 12,
  "color" : "#000FFF",
  "username" : "zakcseen"
}, {
  "x" : 8,
  "y" : 14,
  "color" : "#4266BE",
  "username" : "256456"
}, {
  "x" : 8,
  "y" : 16,
  "color" : "#000000",
  "username" : "MS-ying"
}, {
  "x" : 8,
  "y" : 18,
  "color" : "#002FA7",
  "username" : "can-not-code"
}, {
  "x" : 9,
  "y" : 0,
  "color" : "#FFFFFF",
  "username" : "JimmyiZhang"
}, {
  "x" : 9,
  "y" : 1,
  "color" : "#6090AD",
  "username" : "vcfch843875618"
}, {
  "x" : 9,
  "y" : 3,
  "color" : "#CD2626",
  "username" : "JudgementH"
}, {
  "x" : 9,
  "y" : 4,
  "color" : "#FFC0CB",
  "username" : "xiaobaaaaa"
}, {
  "x" : 9,
  "y" : 5,
  "color" : "#1F1E33",
  "username" : "Bu-zheng"
}, {
  "x" : 9,
  "y" : 6,
  "color" : "#8600FF",
  "username" : "AggieSama"
}, {
  "x" : 9,
  "y" : 7,
  "color" : "#33B8FF",
  "username" : "alvinvinvinvin"
}, {
  "x" : 9,
  "y" : 8,
  "color" : "#ffffcc",
  "username" : "wenjialu"
}, {
  "x" : 9,
  "y" : 9,
  "color" : "#000000",
  "username" : "8790"
}, {
  "x" : 9,
  "y" : 10,
  "color" : "#78DCFA",
  "username" : "sleeper"
}, {
  "x" : 9,
  "y" : 11,
  "color" : "#001000",
  "username" : "xnhlf"
}, {
  "x" : 9,
  "y" : 12,
  "color" : "#ADD8E6",
  "username" : "BlueinkTing"
}, {
  "x" : 9,
  "y" : 13,
  "color" : "#666666",
  "username" : "Angels-D"
}, {
  "x" : 9,
  "y" : 15,
  "color" : "#000000",
  "username" : "Rainxbow"
}, {
  "x" : 9,
  "y" : 17,
  "color" : "#FFFFFF",
  "username" : "retterwang"
}, {
  "x" : 9,
  "y" : 18,
  "color" : "#FFFFFF",
  "username" : "wangzepu"
}, {
  "x" : 9,
  "y" : 19,
  "color" : "#FFFFFF",
  "username" : "hamo"
}, {
  "x" : 10,
  "y" : 0,
  "color" : "#FFFFFF",
  "username" : "chen-qingyu"
}, {
  "x" : 10,
  "y" : 1,
  "color" : "#FFDA53",
  "username" : "zhendan911"
}, {
  "x" : 10,
  "y" : 2,
  "color" : "#9400D3",
  "username" : "XIkariShinji"
}
 , {
  "x" : 10,
  "y" : 3,
  "color" : "#FF0000",
  "username" : "w845661346"
}, {
  "x" : 10,
  "y" : 5,
  "color" : "#66CCFC",
  "username" : "zeranlin"
}, {
  "x" : 10,
  "y" : 6,
  "color" : "#66CCFF",
  "username" : "flakedZZ"
}, {
  "x" : 10,
  "y" : 7,
  "color" : "#00000F",
  "username" : "lcke001"
}, {
  "x" : 10,
  "y" : 8,
  "color" : "#FF0000",
  "username" : "zaishiqingyuan"
}, {
  "x" : 10,
  "y" : 9,
  "color" : "#1A2B3C",
  "username" : "hrbattery"
}, {
  "x" : 10,
  "y" : 10,
  "color" : "#000000",
  "username" : "Yijia-Z"
}, {
  "x" : 10,
  "y" : 11,
  "color" : "#000000",
  "username" : "helianthuswhite"
}, {
  "x" : 10,
  "y" : 12,
  "color" : "#66CCFF",
  "username" : "HeeiYa"
}, {
  "x" : 10,
  "y" : 19,
  "color" : "#FF69B4",
  "username" : "qidianxyz"
}, {
  "x" : 11,
  "y" : 0,
  "color" : "#FFFFFF",
  "username" : "magiciansem"
}, {
  "x" : 11,
  "y" : 1,
  "color" : "#FF8C00",
  "username" : "guojinhao9861"
}, {
  "x" : 11,
  "y" : 3,
  "color" : "#FF0000",
  "username" : "DUKEY-123"
}, {
  "x" : 11,
  "y" : 5,
  "color" : "#738E96",
  "username" : "iwbiu"
}, {
  "x" : 11,
  "y" : 6,
  "color" : "#FF00FF",
  "username" : "nicxzq"
}, {
  "x" : 11,
  "y" : 7,
  "color" : "#FFC0CB",
  "username" : "Yugen-SYSU"
}, {
  "x" : 11,
  "y" : 8,
  "color" : "#FFC0CB",
  "username" : "kangming06"
}, {
  "x" : 11,
  "y" : 9,
  "color" : "#00FFCC",
  "username" : "CamusY"
}, {
  "x" : 11,
  "y" : 10,
  "color" : "#282828",
  "username" : "Charisxxx"
}, {
  "x" : 11,
  "y" : 11,
  "color" : "#454545",
  "username" : "narutobing"
}, {
  "x" : 11,
  "y" : 12,
  "color" : "#F5F5F5",
  "username" : "ChaoSunX"
}, {
  "x" : 11,
  "y" : 15,
  "color" : "#FFFFFF",
  "username" : "NanGua-007"
}, {
  "x" : 11,
  "y" : 17,
  "color" : "#02a2ff",
  "username" : "zengallen8235"
}, {
  "x" : 11,
  "y" : 19,
  "color" : "#000000",
  "username" : "Kiro6123"
}, {
  "x" : 12,
  "y" : 0,
  "color" : "#ff0000",
  "username" : "ILoveYouCC"
}, {
  "x" : 12,
  "y" : 1,
  "color" : "#FE7FF0",
  "username" : "jintaojt6"
}, {
  "x" : 12,
  "y" : 2,
  "color" : "#00FFFF",
  "username" : "Kaervekthespiteful"
}, {
  "x" : 12,
  "y" : 6,
  "color" : "#00CCD4",
  "username" : "Herosi77"
}, {
  "x" : 12,
  "y" : 8,
  "color" : "#009688",
  "username" : "myy0222"
}, {
  "x" : 12,
  "y" : 9,
  "color" : "#ff0000",
  "username" : "ananliangliang"
}, {
  "x" : 12,
  "y" : 10,
  "color" : "#cbff6a",
  "username" : "MayL216"
}, {
  "x" : 12,
  "y" : 11,
  "color" : "#F5F5F5",
  "username" : "ashuanger"
}, {
  "x" : 12,
  "y" : 12,
  "color" : "#0969DA",
  "username" : "fake-zyk"
}, {
  "x" : 12,
  "y" : 16,
  "color" : "#FFFFFF",
  "username" : "DYY313"
}, {
  "x" : 12,
  "y" : 19,
  "color" : "#02a2ff",
  "username" : "bbbhp"
}, {
  "x" : 13,
  "y" : 0,
  "color" : "#FFFFFF",
  "username" : "yangyongron"
}, {
  "x" : 13,
  "y" : 1,
  "color" : "#000000",
  "username" : "LZLEX1"
}, {
  "x" : 13,
  "y" : 3,
  "color" : "#F5F5F5",
  "username" : "Augusterterter"
}, {
  "x" : 13,
  "y" : 6,
  "color" : "#FF0000",
  "username" : "zhaoshengyao"
}, {
  "x" : 13,
  "y" : 8,
  "color" : "#FFFFFF",
  "username" : "rvirtualea9"
}, {
  "x" : 13,
  "y" : 10,
  "color" : "#FF0000",
  "username" : "luoxp770"
}, {
  "x" : 13,
  "y" : 13,
  "color" : "#5588FF",
  "username" : "LamentWy"
}, {
  "x" : 13,
  "y" : 14,
  "color" : "#FFFFFF",
  "username" : "V7ita"
}, {
  "x" : 13,
  "y" : 15,
  "color" : "#FE7600",
  "username" : "Leasekj"
}, {
  "x" : 14,
  "y" : 0,
  "color" : "#808080",
  "username" : "ActionDing"
}, {
  "x" : 14,
  "y" : 3,
  "color" : "#F5F5F5",
  "username" : "fengfeifang"
}, {
  "x" : 14,
  "y" : 5,
  "color" : "#0000FF",
  "username" : "jiaoff-hub"
}, {
  "x" : 14,
  "y" : 14,
  "color" : "#FFFFFF",
  "username" : "Renmie"
}, {
  "x" : 14,
  "y" : 17,
  "color" : "#FFFFFF",
  "username" : "hklkfm"
}, {
  "x" : 15,
  "y" : 0,
  "color" : "#FFFFFF",
  "username" : "toten1982"
}, {
  "x" : 15,
  "y" : 1,
  "color" : "#8EE4FA",
  "username" : "caoyuqian1"
}, {
  "x" : 15,
  "y" : 2,
  "color" : "#0000CD",
  "username" : "WHJ1928"
}, {
  "x" : 15,
  "y" : 5,
  "color" : "#FF0000",
  "username" : "RayLannis"
}, {
  "x" : 15,
  "y" : 7,
  "color" : "#FFDA55",
  "username" : "ConnorFV"
}, {
  "x" : 15,
  "y" : 11,
  "color" : "#8EE4FA",
  "username" : "ChTea"
}, {
  "x" : 15,
  "y" : 15,
  "color" : "#FFFFFF",
  "username" : "AQ98420"
}, {
  "x" : 15,
  "y" : 17,
  "color" : "#66CCFF",
  "username" : "ABCPAN-rank"
}, {
  "x" : 15,
  "y" : 19,
  "color" : "#FFFFFF",
  "username" : "maquan0927"
}, {
  "x" : 16,
  "y" : 0,
  "color" : "#33CEFA",
  "username" : "caozhzh"
}, {
  "x" : 16,
  "y" : 3,
  "color" : "#66CCFF",
  "username" : "angels-blessing"
}, {
  "x" : 16,
  "y" : 7,
  "color" : "#FFDA53",
  "username" : "lanfeitiao"
}, {
  "x" : 16,
  "y" : 9,
  "color" : "#fff333",
  "username" : "khsing"
}, {
  "x" : 16,
  "y" : 10,
  "color" : "#000000",
  "username" : "haozhuang"
}, {
  "x" : 16,
  "y" : 12,
  "color" : "#87CEFA",
  "username" : "Lcomerun"
}, {
  "x" : 16,
  "y" : 15,
  "color" : "#8EE4FA",
  "username" : "huangYD8080"
}, {
  "x" : 16,
  "y" : 16,
  "color" : "#66CCFF",
  "username" : "yyq90"
}, {
  "x" : 16,
  "y" : 19,
  "color" : "#FF0000",
  "username" : "EnergyMaking"
}, {
  "x" : 17,
  "y" : 0,
  "color" : "#FE0A0C",
  "username" : "MeteorAndy"
}, {
  "x" : 17,
  "y" : 3,
  "color" : "#b36d61",
  "username" : "kaifanlezz"
}, {
  "x" : 17,
  "y" : 6,
  "color" : "#00CCFF",
  "username" : "gudaoxifengshouma"
}, {
  "x" : 17,
  "y" : 16,
  "color" : "#FF0000",
  "username" : "dg3117"
}, {
  "x" : 17,
  "y" : 17,
  "color" : "#00FFE6",
  "username" : "Alexxx1120"
}, {
  "x" : 17,
  "y" : 18,
  "color" : "#E65D6E",
  "username" : "742087271"
}, {
  "x" : 17,
  "y" : 19,
  "color" : "#FFFFFF",
  "username" : "jiargcn"
}, {
  "x" : 18,
  "y" : 0,
  "color" : "#66CCFF",
  "username" : "guoxiaobie"
}, {
  "x" : 18,
  "y" : 1,
  "color" : "#3CAEA3",
  "username" : "hsldymq"
}, {
  "x" : 18,
  "y" : 3,
  "color" : "#0000FF",
  "username" : "FalseK"
}, {
  "x" : 18,
  "y" : 12,
  "color" : "#FFFFFF",
  "username" : "fibercoke"
}, {
  "x" : 18,
  "y" : 15,
  "color" : "#FFFFFF",
  "username" : "755328872"
}, {
  "x" : 18,
  "y" : 18,
  "color" : "#FFFFFF",
  "username" : "super14342"
}, {
  "x" : 18,
  "y" : 19,
  "color" : "#1453AD",
  "username" : "firepond"
}, {
  "x" : 19,
  "y" : 0,
  "color" : "#66CCFF",
  "username" : "tythen"
}, {
  "x" : 19,
  "y" : 1,
  "color" : "#00CBD4",
  "username" : "vlzz1221"
}, {
  "x" : 19,
  "y" : 2,
  "color" : "#FE77F0",
  "username" : "camiao"
}, {
  "x" : 19,
  "y" : 4,
  "color" : "#39c5bb",
  "username" : "miku122"
}, {
  "x" : 19,
  "y" : 6,
  "color" : "#FFFFFF",
  "username" : "whiplashf"
}, {
  "x" : 19,
  "y" : 7,
  "color" : "#FFFFFF",
  "username" : "TedGr"
}, {
  "x" : 19,
  "y" : 8,
  "color" : "#FFFFFF",
  "username" : "BestOverall"
}, {
  "x" : 19,
  "y" : 10,
  "color" : "#000000",
  "username" : "StormChen94"
}, {
  "x" : 19,
  "y" : 17,
  "color" : "#00BFFF",
  "username" : "luguo-ing"
}, {
  "x" : 19,
  "y" : 18,
  "color" : "#F5F5F5",
  "username" : "cai895015380"
}, {
  "x" : 19,
  "y" : 19,
  "color" : "#FFFFFF",
  "username" : "chengww5217"
}, {
  "x" : 12,
  "y" : 4,
  "color" : "#146e3c",
  "username" : "gaoyang97"
}, {
  "x" : 14,
  "y" : 10,
  "color" : "#830303",
  "username" : "nekooooooooooooooooooo"
}, {
  "x" : 12,
  "y" : 7,
  "color" : "#FF0000",
  "username" : "wangxu400320"
}, {
  "x" : 16,
  "y" : 14,
  "color" : "#FF0000",
  "username" : "Zjd12138"
}, {
  "x" : 16,
  "y" : 18,
  "color" : "#FF0000",
  "username" : "funusb"
}, {
  "x" : 3,
  "y" : 18,
  "color" : "#0096BF",
  "username" : "seanYibo"
}, {
  "x" : 13,
  "y" : 18,
  "color" : "#AA44CC",
  "username" : "VioletLi"
}, {
  "x" : 2,
  "y" : 3,
  "color" : "#AFEEEE",
  "username" : "wennycai"
}, {
  "x" : 12,
  "y" : 13,
  "color" : "#AFEFFF",
  "username" : "ikm565"
}, {
  "x" : 12,
  "y" : 15,
  "color" : "#2345FF",
  "username" : "Zzz2233"
}, {
  "x" : 19,
  "y" : 13,
  "color" : "#2345FF",
  "username" : "Forzakenmore"
}, {
  "x" : 9,
  "y" : 14,
  "color" : "#2345FF",
  "username" : "dplrwj"
},{
  "x" : 10,
  "y" : 13,
  "color" : "#2345FF",
  "username" : "patricknorj"
},{
  "x" : 13,
  "y" : 12,
  "color" : "#FAFAFA",
  "username" : "Thora666"
},{
  "x" : 10,
  "y" : 18,
  "color" : "#9DDA93",
  "username" : "moonlightman"
},{
  "x" : 2,
  "y" : 9,
  "color" : "#FF0000",
  "username" : "Rehtt"
},{
  "x" : 15,
  "y" : 18,
  "color" : "#FF0000",
  "username" : "lxy96Scorpion"
},{
  "x" : 2,
  "y" : 19,
  "color" : "#FF0000",
  "username" : "roc198"
},{
  "x" : 4,
  "y" : 19,
  "color" : "#FF0000",
  "username" : "786575099"
}, {
  "x" : 0,
  "y" : 15,
  "color" : "#FF0000",
  "username" : "Caement"
}, {
  "x" : 14,
  "y" : 19,
  "color" : "#2E3092",
  "username" : "selltk"
}, {
  "x" : 3,
  "y" : 14,
  "color" : "#0000FF",
  "username" : "nvknow"
}, {
  "x" : 1,
  "y" : 5,
  "color" : "#FFFFFF",
  "username" : "321SONG321"
}, {
  "x" : 19,
  "y" : 9,
  "color" : "#FFFFFF",
  "username" : "lycheew9"
}, {
  "x" : 14,
  "y" : 1,
  "color" : "#4b4843",
  "username" : "Spico197"
}, {
  "x" : 5,
  "y" : 8,
  "color" : "#81b29a",
  "username" : "staticfire"
}, {
  "x" : 4,
  "y" : 11,
  "color" : "#00ff00",
  "username" : "gbh124"
}, {
  "x" : 7,
  "y" : 2,
  "color" : "#ffffff",
  "username" : "Smart-Yi"
}
 , {
  "x" : 4,
  "y" : 9,
  "color" : "#4b4843",
  "username" : "pikaqiu420"
}, {
  "x" : 11,
  "y" : 18,
  "color" : "#000000",
  "username" : "lllail"
}
 , {
  "x" : 14,
  "y" : 12,
  "color" : "#4b4933",
  "username" : "xiuqizhip1ng"
}, {
  "x" : 14,
  "y" : 18,
  "color" : "#4b4933",
  "username" : "Chinanumb"
}, {
  "x" : 10,
  "y" : 4,
  "color" : "#0000FF",
  "username" : "wasserflut"
}, {
  "x" : 18,
  "y" : 6,
  "color" : "#57faff",
  "username" : "13049293603"
}, {
  "x" : 11,
  "y" : 4,
  "color" : "#57faff",
  "username" : "TOHSAKA-RINN"
}, {
  "x" : 6,
  "y" : 12,
  "color" : "#0011AA",
  "username" : "Avo6"
},{
  "x" : 16,
  "y" : 1,
  "color" : "#0011AA",
  "username" : "mobiusstrip1"
}
]
